InfoImputer/Auto.py
InfoImputer/__init__.py
info_imputer-0.0.1.dist-info/METADATA
info_imputer-0.0.1.dist-info/WHEEL
info_imputer-0.0.1.dist-info/licenses/license.txt
info_imputer-0.0.1.dist-info/RECORD
