Metadata-Version: 2.1
Name: Info-Imputer
Version: 0.0.1
Summary: A wise imputer that fill missing values for each features by deriving information from other correlated-informative features.
Author: KhashayarRahimi
License-File: license.txt
Classifier: License :: OSI Approved :: MIT License
Classifier: Operating System :: OS Independent
Classifier: Programming Language :: Python :: 3
Requires-Python: >=3.7
